baalib/__init__.py
baalib/baalib.egg-info/PKG-INFO
baalib/baalib.egg-info/SOURCES.txt
baalib/baalib.egg-info/dependency_links.txt
baalib/baalib.egg-info/top_level.txt
baalib/logger.py
baalib/networking.py
baalib-0.0.9.dist-info/LICENSE
baalib-0.0.9.dist-info/METADATA
baalib-0.0.9.dist-info/WHEEL
baalib-0.0.9.dist-info/RECORD
